uc_sgsim/__init__.py
uc_sgsim/exception.py
uc_sgsim/random_field.py
uc_sgsim/sgsim.py
uc_sgsim/utils.py
uc_sgsim/c_core/uc_sgsim.dll
uc_sgsim/c_core/uc_sgsim.so
uc_sgsim/cov_model/__init__.py
uc_sgsim/cov_model/base.py
uc_sgsim/cov_model/model.py
uc_sgsim/kriging/__init__.py
uc_sgsim/kriging/base.py
uc_sgsim/kriging/kriging.py
uc_sgsim/plotting/__init__.py
uc_sgsim/plotting/base.py
uc_sgsim/plotting/sgsim_plot.py
uc_sgsim-1.2.10.dist-info/LICENSE.md
uc_sgsim-1.2.10.dist-info/METADATA
uc_sgsim-1.2.10.dist-info/WHEEL
uc_sgsim-1.2.10.dist-info/top_level.txt
uc_sgsim-1.2.10.dist-info/RECORD
